{
  "boTyp": "MARKTLOKATION",
  "versionStruktur": "1",
  "marktlokationsId": "40975495000",
  "sparte": "sed voluptate cupidatat amet in",
  "energierichtung": "AUSSP",
  "bilanzierungsmethode": "TLP_GEMEINSAM",
  "verbrauchsart": "SW",
  "unterbrechbar": true,
  "netzebene": "ND",
  "umspannung": "MSP_NSP_UMSP",
  "netzbetreiberCodeNr": "5980050970",
  "gebietTyp": "AREALNETZ",
  "netzgebietNr": "5439859848",
  "bilanzierungsgebiet": "id ad",
  "grundversorgerCodeNr": "8960277289",
  "gasqualitaet": "L_GAS",
  "endkunde": {
    "boTyp": "GESCHAEFTSPARTNER",
    "versionStruktur": "1",
    "anrede": "Herr",
    "name1": "Heinig",
    "name2": "Lee",
    "name3": "culpa",
    "name4": "deserunt Excepteur",
    "umsatzsteuerId": "DE111000111",
    "glaeubigerId": "195659",
    "emailAdresse": "Sena_Thone@gmail.com",
    "website": "https://vermittelnd-faschismus.com/",
    "gewerbekennzeichnung": true,
    "hrnummer": "776798",
    "amtsgericht": "Karlsruhe",
    "partneradresse": {
      "postleitzahl": "27484",
      "ort": "Nicoburg",
      "strasse": "In der Wüste",
      "hausnummer": "6",
      "postfach": "Excepteur ex do dolore anim",
      "adresszusatz": "deserunt consequat",
      "coErgaenzung": "voluptate sunt",
      "landescode": "JM",
      "ortsteil": "Ost Marvin",
      "zusatzInformation": {
        "zusatz1": "Duis dolor pariatur proident",
        "zusatz2": "mollit id eu voluptate officia",
        "zusatz3": "id sunt",
        "zusatz4": "et sunt ut aute",
        "zusatz5": "eu"
      }
    },
    "externeKundenummerLieferant": "133583",
    "externeReferenzen": [
      {
        "exRefName": "Kundennummer beim Altlieferanten",
        "exRefWert": "2247573770"
      }
    ],
    "geschaeftspartnerrolle": [
      "EIGENTUEMER"
    ],
    "kontaktweg": [
      "ANSCHREIBEN"
    ]
  },
  "lokationsadresse": {
    "postleitzahl": "52769",
    "ort": "Korbinianburg",
    "strasse": "Kumper Weg",
    "hausnummer": "89",
    "postfach": "voluptate aliqua fugiat irure reprehenderit",
    "adresszusatz": "enim in nulla",
    "coErgaenzung": "non commodo nisi",
    "landescode": "SV",
    "ortsteil": "Bad Nike",
    "zusatzInformation": {
      "zusatz1": "nostrud Duis Lorem",
      "zusatz2": "in consequat commodo nostrud amet",
      "zusatz3": "qui commodo aliqua",
      "zusatz4": "dolor et sunt",
      "zusatz5": "officia aliquip cupidatat"
    }
  },
  "katasterinformation": {
    "gemarkung_flur": "esse in eiusmod Ut",
    "flurstueck": "labore in consectetur consequat quis"
  },
  "regelzone": "incididunt culpa dolore proident laborum",
  "marktgebiet": "sint",
  "zeitreihentyp": "SLS",
  "messtechnischeEinordnung": "KEINE_MESSUNG",
  "sperrstatus": "ENTSPERRT",
  "referenzMarktlokationsId": "95106160883",
  "versorgungsart": "ERSATZVERSORGUNG",
  "eigentuemer": {
    "boTyp": "GESCHAEFTSPARTNER",
    "versionStruktur": "1",
    "anrede": "Herr",
    "name1": "Waldmann",
    "name2": "Jannes",
    "name3": "amet sit sed officia cupidatat",
    "name4": "quis",
    "umsatzsteuerId": "DE001001110",
    "glaeubigerId": "732713",
    "emailAdresse": "Ivan87@yahoo.com",
    "website": "https://magisch-schwangerschaft.de",
    "gewerbekennzeichnung": false,
    "hrnummer": "445623",
    "amtsgericht": "Süd Fredericscheid",
    "partneradresse": {
      "postleitzahl": "18279",
      "ort": "Abduldorf",
      "strasse": "Teltower Str.",
      "hausnummer": "39c",
      "postfach": "ea amet elit adipisicing dolor",
      "adresszusatz": "proident dolor non eiusmod Duis",
      "coErgaenzung": "laboris ullamco Excepteur non eu",
      "landescode": "IQ",
      "ortsteil": "Barrstadt",
      "zusatzInformation": {
        "zusatz1": "enim eiusmod",
        "zusatz2": "incididunt",
        "zusatz3": "aliquip",
        "zusatz4": "dolore culpa",
        "zusatz5": "dolore sed"
      }
    },
    "externeKundenummerLieferant": "121367",
    "externeReferenzen": [
      {
        "exRefName": "Kundennummer beim Lieferanten",
        "exRefWert": "9449400846"
      }
    ],
    "geschaeftspartnerrolle": [
      "ABLESEKARTENEMPFAENGER"
    ],
    "kontaktweg": [
      "SMS"
    ]
  },
  "hausverwalter": {
    "boTyp": "GESCHAEFTSPARTNER",
    "versionStruktur": "1",
    "anrede": "Dr.",
    "name1": "Többen",
    "name2": "Leroy",
    "name3": "pariatur",
    "name4": "dolor velit aliquip ex laborum",
    "umsatzsteuerId": "DE010101000",
    "glaeubigerId": "597992",
    "emailAdresse": "Ali.Timmermann27@yahoo.com",
    "website": "https://kunstvoll-astronomie.info/",
    "gewerbekennzeichnung": true,
    "hrnummer": "202864",
    "amtsgericht": "Bayreuth",
    "partneradresse": {
      "postleitzahl": "26694",
      "ort": "Sydneyland",
      "strasse": "Lohrbergstr.",
      "hausnummer": "48c",
      "postfach": "sunt",
      "adresszusatz": "est sint velit fugiat in",
      "coErgaenzung": "adipisicing minim voluptate",
      "landescode": "SU",
      "ortsteil": "Süd Milandorf",
      "zusatzInformation": {
        "zusatz1": "Ut",
        "zusatz2": "eiusmod dolor",
        "zusatz3": "reprehenderit sed qui Duis",
        "zusatz4": "nulla cupidatat veniam consectetur",
        "zusatz5": "incididunt officia ut dolor"
      }
    },
    "externeKundenummerLieferant": "790804",
    "externeReferenzen": [
      {
        "exRefName": "Kundennummer beim Altlieferanten",
        "exRefWert": "2812294962"
      }
    ],
    "geschaeftspartnerrolle": [
      "INTERESSENT"
    ],
    "kontaktweg": [
      "E_MAIL"
    ]
  },
  "verguetungEmpfaenger": "LIEFERANT",
  "statusErzeugendeMalo": "GEFOERDERTE_DIREKTVERMARKTUNG",
  "fernsteuerbarkeit": "TECHNISCH_NICHT_FERNSTEUERBAR",
  "foerderungsLand": "enim",
  "redispatch": true,
  "zukuenftigerMeldepunkt": false,
  "lokationszuordnung": "ENDET",
  "konfigurationsprodukt": "sit",
  "leistungskurvendefinition": "ea quis nisi fugiat incididunt",
  "produktdatenRelevanteRolle": "BIKO",
  "beteiligterMarktpartner": {
    "boTyp": "MARKTTEILNEHMER",
    "versionStruktur": "1",
    "geschaeftspartnerrolle": "INTERESSENT",
    "anrede": "Frau",
    "name1": "Hornung",
    "name2": "Aliya",
    "name3": "irure mollit est eiusmod",
    "name4": "aliqua voluptate ad nostrud dolor",
    "partneradresse": {
      "postleitzahl": "35891",
      "ort": "Neu Calvin",
      "strasse": "Amselweg",
      "hausnummer": "668",
      "postfach": "in officia elit enim",
      "adresszusatz": "dolor minim ut in laboris",
      "coErgaenzung": "quis laboris Duis",
      "landescode": "TW",
      "ortsteil": "Bad Nika",
      "zusatzInformation": {
        "zusatz1": "adipisicing",
        "zusatz2": "cupidatat ex",
        "zusatz3": "culpa labore sed",
        "zusatz4": "laborum elit laboris",
        "zusatz5": "officia deserunt in"
      }
    },
    "gewerbekennzeichnung": true,
    "externeKundenummerLieferant": "voluptate",
    "marktrolle": "EIV",
    "rollencodenummer": "357533721",
    "rollencodetyp": "cillum voluptate velit",
    "umsatzsteuerId": "DE111011000",
    "steuernummer": "365807135",
    "ansprechpartner": {
      "boTyp": "ANSPRECHPARTNER",
      "versionStruktur": "1",
      "nachname": "Gebhardt",
      "eMailAdresse": "Elia.Engelmann19@gmail.com",
      "rufnummern": [
        {
          "nummerntyp": "RUF_ZENTRALE",
          "rufnummer": "(0621) 128100075"
        }
      ]
    },
    "makoadresse": "esse",
    "downloadlinkZertifikat": "https://gewitzt-kupfer.info",
    "amtsgericht": "Bartelsburg",
    "hrnummer": "058401",
    "website": "https://ratlos-okologie.de/",
    "faxnummer": "+49-7578-76628751",
    "kommunikationsrolle": "NETZANSCHLUSS_ANLAGEN",
    "weiterverpflichtet": false,
    "kommunikationsparameter": {
      "zieladresse": {
        "zieladresse1": "dolore enim",
        "zieladresse2": "dolor nulla",
        "zieladresse3": "adipisicing",
        "zieladresse4": "amet velit anim cillum est",
        "zieladresse5": "ut anim culpa ullamco"
      },
      "zertifikatsAussteller": {
        "zertifikatsAussteller1": "fugiat",
        "zertifikatsAussteller2": "elit deserunt aliquip dolor culpa",
        "zertifikatsAussteller3": "labore in culpa cupidatat",
        "zertifikatsAussteller4": "do laboris nisi enim ullamco",
        "zertifikatsAussteller5": "occaecat ad Excepteur voluptate nostrud"
      },
      "zertifikatsNutzer": {
        "zertifikatsNutzer1": "consectetur",
        "zertifikatsNutzer2": "incididunt in Ut",
        "zertifikatsNutzer3": "in officia ad minim",
        "zertifikatsNutzer4": "velit magna",
        "zertifikatsNutzer5": "non"
      }
    },
    "messstellenbetreiberEigenschaft": "AUFFANGMESSSTELLENBETREIBER",
    "bankverbindung": [
      {
        "verwendungszweck": "BV_SONSTIGE",
        "iban": "GI35FARP6J4560613250270",
        "kontoinhaber": "Angelo Piesker",
        "bic": "XRHJGQIVO3F",
        "kreditinstitut": "Eberhard-Nannen"
      }
    ],
    "erreichbarkeit": [
      {
        "verfuegbarkeit": "MONTAG",
        "zeit": "sed dolore magna"
      }
    ]
  },
  "modulNetzentgelte": "ANREIZMODUL_ZEITVARIABLES_NETZENTGELT_MODUL_3",
  "marktrollen": [
    {
      "boTyp": "MARKTTEILNEHMER",
      "versionStruktur": "1",
      "geschaeftspartnerrolle": "ABLESEKARTENEMPFAENGER",
      "anrede": "Herr",
      "name1": "Kedzierski",
      "name2": "Evelin",
      "name3": "pariatur laboris",
      "name4": "fugiat commodo",
      "partneradresse": {
        "postleitzahl": "55520",
        "ort": "Neuss",
        "strasse": "Bendenweg",
        "hausnummer": "3",
        "postfach": "consequat nulla cupidatat",
        "adresszusatz": "laborum labore tempor commodo",
        "coErgaenzung": "ad ex labore",
        "landescode": "GM",
        "ortsteil": "Knetschburg",
        "zusatzInformation": {
          "zusatz1": "consequat sint",
          "zusatz2": "aliqua minim nulla nostrud anim",
          "zusatz3": "Lorem",
          "zusatz4": "nisi",
          "zusatz5": "reprehenderit"
        }
      },
      "gewerbekennzeichnung": true,
      "externeKundenummerLieferant": "labore nulla",
      "marktrolle": "UENB",
      "rollencodenummer": "963829162",
      "rollencodetyp": "sit anim",
      "umsatzsteuerId": "DE110110000",
      "steuernummer": "612893584",
      "ansprechpartner": {
        "boTyp": "ANSPRECHPARTNER",
        "versionStruktur": "1",
        "nachname": "Frank",
        "eMailAdresse": "Louise5@yahoo.com",
        "rufnummern": [
          {
            "nummerntyp": "RUF_ZENTRALE",
            "rufnummer": "+49-797-8351264"
          }
        ]
      },
      "makoadresse": "ea cupidatat in",
      "downloadlinkZertifikat": "https://korrekt-gold.ch",
      "amtsgericht": "Roosstadt",
      "hrnummer": "271449",
      "website": "https://behutsam-schwert.name",
      "faxnummer": "+49-7227-40364621",
      "kommunikationsrolle": "RAHMENVERTRAEGE",
      "weiterverpflichtet": true,
      "kommunikationsparameter": {
        "zieladresse": {
          "zieladresse1": "ea officia",
          "zieladresse2": "proident eu",
          "zieladresse3": "ex magna",
          "zieladresse4": "adipisicing",
          "zieladresse5": "sit cupidatat quis"
        },
        "zertifikatsAussteller": {
          "zertifikatsAussteller1": "ea officia",
          "zertifikatsAussteller2": "deserunt ullamco velit nisi",
          "zertifikatsAussteller3": "aliqua Excepteur ea",
          "zertifikatsAussteller4": "voluptate",
          "zertifikatsAussteller5": "commodo aliqua in"
        },
        "zertifikatsNutzer": {
          "zertifikatsNutzer1": "ullamco dolore magna consectetur culpa",
          "zertifikatsNutzer2": "sed do",
          "zertifikatsNutzer3": "laborum veniam tempor Lorem",
          "zertifikatsNutzer4": "velit dolor ut et reprehenderit",
          "zertifikatsNutzer5": "non Excepteur irure occaecat ipsum"
        }
      },
      "messstellenbetreiberEigenschaft": "AUFFANGMESSSTELLENBETREIBER",
      "bankverbindung": [
        {
          "verwendungszweck": "BV_ZAHLUNG_MMMA",
          "iban": "DK2018236603006090",
          "kontoinhaber": "Tobias Farber",
          "bic": "MYXAPTS3",
          "kreditinstitut": "Tschirch UG"
        }
      ],
      "erreichbarkeit": [
        {
          "verfuegbarkeit": "DIENSTAG",
          "zeit": "fugiat nostrud eiusmod"
        }
      ]
    }
  ],
  "zaehlwerke": [
    {
      "zaehlwerkId": "980198561",
      "bezeichnung": "officia",
      "richtung": "EINSP",
      "obisKennzahl": "esse",
      "wandlerfaktor": 2.5,
      "einheit": "STUNDE",
      "schwachlastfaehig": "SCHWACHLASTFAEHIG",
      "verbrauchsart": "KL",
      "unterbrechbarkeit": "UV",
      "waermenutzung": "SPEICHERHEIZUNG",
      "konzessionsabgabe": {
        "satz": "TSS",
        "kosten": -54550594.15341048,
        "kategorie": "sed culpa cupidatat minim"
      },
      "steuerbefreit": true,
      "vorkommastelle": 7,
      "nachkommastelle": 3,
      "abrechnungsrelevant": true,
      "anzahlAblesungen": false,
      "zaehlzeiten": {
        "satz": "TS",
        "register": "dolor commodo",
        "zaehlzeitDefinition": "reprehenderit dolor magna",
        "schwachlastfaehig": "NICHT_SCHWACHLASTFAEHIG"
      },
      "konfiguration": "Lorem",
      "messprodukt": "voluptate sed Excepteur ipsum",
      "wertegranularitaet": "MONATLICH",
      "notwendigkeitZweiteMessung": "VORHANDEN",
      "werteuebermittlungVerwendungszweck": "NICHT_VORHANDEN",
      "artEMobilitaet": "LS",
      "konfigurationsprodukt": "nostrud proident",
      "keinKonfigurationsprodukt": false,
      "leistungskurvendefinition": "adipisicing proident",
      "verwendungszwecke": [
        {
          "marktrolle": "INTERESSENT",
          "zweck": [
            "MEHRMINDERMENGENABRECHNUNG"
          ]
        }
      ]
    }
  ],
  "zaehlwerkeBeteiligteMarktrolle": [
    "RB"
  ],
  "verbrauchsmenge": [
    {
      "startdatum": "1946-02-10T02:23:55.0Z",
      "enddatum": "1901-08-17T03:18:16.0Z",
      "wertermittlungsverfahren": "PROGNOSE",
      "messwertstatus": "ERSATZWERT",
      "obiskennzahl": "mollit sunt velit do deserunt",
      "wert": 16.5,
      "einheit": "VARH",
      "type": "VERANSCHLAGTEJAHRESMENGE",
      "tarifstufe": "TARIFSTUFE_2",
      "nutzungszeitpunkt": "1965-09-12T03:12:56.0Z",
      "ausfuehrungszeitpunkt": "1923-01-09T08:51:19.0Z",
      "position": 2813250102,
      "ablesedatum": "1930-06-18T05:20:36.0Z",
      "leistungsperiode": "287262",
      "statuszusatzinformationen": [
        {
          "art": "MESSKLASSIFIZIERUNG",
          "status": "KEIN_ZUGANG"
        }
      ]
    }
  ],
  "zugehoerigeMesslokationen": [
    {
      "messlokationsId": "192664157217655728074796458349902",
      "arithmetik": "ADDITION",
      "gueltigSeit": "1912-10-27T08:32:29.0Z",
      "gueltigBis": "1946-08-08T11:46:40.0Z"
    }
  ],
  "netznutzungsabrechnungsdaten": [
    {
      "artikelId": "6077853844",
      "artikelIdTyp": "GRUPPENARTIKELID",
      "anzahl": 4,
      "gemeinderabatt": 1.25,
      "zuschlag": 2,
      "abschlag": 7.75,
      "singulaereBetriebsmittel": {
        "wert": 1.25,
        "einheit": "KWH"
      },
      "preisSingulaereBetriebsmittel": {
        "wert": 1,
        "einheit": "EUR",
        "bezugswert": "KWH",
        "status": "ENDGUELTIG"
      },
      "abrechnungBlindarbeit": false,
      "zahlerBlindarbeit": "ANSCHLUSSNUTZER",
      "zahlerBlindarbeitLf": false,
      "zaehlzeiten": {
        "satz": "TS",
        "register": "ex ut",
        "zaehlzeitDefinition": "elit",
        "schwachlastfaehig": "NICHT_SCHWACHLASTFAEHIG"
      }
    }
  ],
  "messstellenbetriebsabrechnungsdaten": [
    {
      "messstellenbetriebsabrechnung": false,
      "artikelId": "4668754121",
      "artikelIdTyp": "GRUPPENARTIKELID",
      "anzahl": 6,
      "zuschlag": 7.5,
      "abschlag": 7.5
    }
  ],
  "energieherkunft": [
    {
      "erzeugungsart": "BIOMASSE",
      "anteilProzent": 14
    }
  ]
}