{
  "boTyp": "SCHALTZEITDEFINITION",
  "versionStruktur": "1",
  "beginndatum": "1967-09-24T10:14:45.0Z",
  "endedatum": "1946-05-04T12:21:45.0Z",
  "version": "1901-08-11T19:15:07.0Z",
  "code": "CODE_010001",
  "notwendigkeit": "ZAEHLZEITDEFINITIONEN_WERDEN_NICHT_VERWENDET",
  "schaltzeiten": [
    {
      "code": "CODE_110010",
      "aenderungszeitpunkt": "1968-01-03T12:04:24.0Z",
      "haeufigkeit": "JAEHRLICH",
      "uebermittelbarkeit": "ELEKTRONISCH",
      "schalthandlung": "LEISTUNG_AN",
      "konfigurationsprodukt": "in et aliquip dolore"
    }
  ]
}