{
  "boTyp": "WERTE_NACH_TYP2",
  "versionStruktur": "1",
  "konfigurationsprodukt": "minim mollit ut",
  "messprodukt": "exercitation in dolor Duis",
  "zieladresse": {
    "zieladresse1": "dolor fugiat mollit",
    "zieladresse2": "proident magna sed",
    "zieladresse3": "ut magna",
    "zieladresse4": "eiusmod do non nostrud",
    "zieladresse5": "Ut"
  },
  "aussteller": {
    "aussteller1": "deserunt in ullamco fugiat sed",
    "aussteller2": "minim veniam",
    "aussteller3": "sed veniam consectetur",
    "aussteller4": "sunt laboris",
    "aussteller5": "amet"
  },
  "zertifikatsNutzer": {
    "zertifikatsNutzer1": "irure",
    "zertifikatsNutzer2": "elit consectetur cupidatat",
    "zertifikatsNutzer3": "ex cupidatat exercitation tempor labore",
    "zertifikatsNutzer4": "pariatur anim",
    "zertifikatsNutzer5": "do"
  },
  "aenderungsmoeglichkeitKonfiguration": "NICHT_ERFORDERLICH",
  "schwellwerte": [
    {
      "obererSchwellwert": 15,
      "untererSchwellwert": 7,
      "konfigurationsprodukt": "KONF_0110"
    }
  ]
}