{
  "boTyp": "ZAEHLER",
  "versionStruktur": "1",
  "zaehlernummer": "ZAEHLER_011111",
  "sparte": "WASSER",
  "zaehlerauspraegung": "ZWEIRICHTUNGSZAEHLER",
  "zaehlertyp": "TURBINENRADGASZAEHLER",
  "tarifart": "MEHRTARIF",
  "zaehlerkonstante": 15,
  "eichungBis": "1928-11-11T22:27:58.0Z",
  "zaehlerhersteller": {
    "boTyp": "GESCHAEFTSPARTNER",
    "versionStruktur": "1",
    "anrede": "Prof. Dr.",
    "name1": "Reus",
    "name2": "Annabelle",
    "name3": "sed",
    "name4": "id in ipsum",
    "umsatzsteuerId": "DE011011100",
    "glaeubigerId": "115122",
    "emailAdresse": "Sean_Zipse@gmail.com",
    "website": "https://entzuckend-lange.org/",
    "gewerbekennzeichnung": true,
    "hrnummer": "078106",
    "amtsgericht": "Bad Malikscheid",
    "partneradresse": {
      "postleitzahl": "82943",
      "ort": "West Loladorf",
      "strasse": "Elisenstr.",
      "hausnummer": "5",
      "postfach": "Lorem esse",
      "adresszusatz": "Ut fugiat eiusmod",
      "coErgaenzung": "ullamco",
      "landescode": "GR",
      "ortsteil": "Süd Leylaburg",
      "zusatzInformation": {
        "zusatz1": "magna non proident dolore",
        "zusatz2": "labore qui",
        "zusatz3": "ea id veniam",
        "zusatz4": "amet est sit ut",
        "zusatz5": "ex nulla nisi ad quis"
      }
    },
    "externeKundenummerLieferant": "446861",
    "externeReferenzen": [
      {
        "exRefName": "Kundennummer beim Altlieferanten",
        "exRefWert": "8919513674"
      }
    ],
    "geschaeftspartnerrolle": [
      "DIENSTLEISTER"
    ],
    "kontaktweg": [
      "TELEFONAT"
    ]
  },
  "gateway": "GATEWAY_100100",
  "fernschaltung": "NICHT_VORHANDEN",
  "messwerterfassung": "FERNAUSLESBAR",
  "zaehlertypspezifikation": "SONSTIGER_EHZ",
  "befestigungsart": "STECKTECHNIK",
  "zaehlergroesse": "MODEM_GSM_M_LG",
  "mengenumwertertyp": "TEMPERATURMENGENUMWERTER",
  "volumenerfassung": "SCHLEICHMENGENUNTERDRUECKUNG",
  "serialnummer": "1755248745",
  "geraetemerkmal": "WASSER_WZ04",
  "herstellungsdatum": "1949-05-21T16:07:45.0Z",
  "baujahr": "elit velit commodo Lorem nostrud",
  "messlokationsId": "354781137590351236823596287399031",
  "marktlokationsId": "77534903716",
  "geraete": [
    {
      "geraetetyp": "TURBINENRADGASZAEHLER",
      "bezeichnung": "fugiat laboris",
      "geraetenummer": "04391",
      "geraetereferenz": "REF_011011",
      "geraeteeigenschaften": {
        "geraetetyp": "MESSDATENREGISTRIERGERAET",
        "geraetemerkmal": "WASSER_VWZ07",
        "faktor": 7.75
      },
      "volumenerfassung": "HOCHFREQUENZSONDE",
      "weitereGeraetenummern": [
        "12130"
      ]
    }
  ],
  "zaehlwerke": [
    {
      "zaehlwerkId": "486549135",
      "bezeichnung": "ut Lorem in",
      "richtung": "EINSP",
      "obisKennzahl": "cupidatat in occaecat",
      "wandlerfaktor": 1.5,
      "einheit": "KWH",
      "schwachlastfaehig": "SCHWACHLASTFAEHIG",
      "verbrauchsart": "KL",
      "unterbrechbarkeit": "NUV",
      "waermenutzung": "WAERMEPUMPE_WAERME",
      "konzessionsabgabe": {
        "satz": "SAS",
        "kosten": 87786373.57316011,
        "kategorie": "do fugiat et"
      },
      "steuerbefreit": false,
      "vorkommastelle": 6,
      "nachkommastelle": 6,
      "abrechnungsrelevant": false,
      "anzahlAblesungen": 4,
      "zaehlzeiten": {
        "register": "deserunt nostrud labore enim exercitation",
        "zaehlzeitDefinition": "cillum anim fugiat",
        "schwachlastfaehig": "NICHT_SCHWACHLASTFAEHIG"
      },
      "konfiguration": "adipisicing dolor mollit incididunt ex",
      "messprodukt": "elit",
      "wertegranularitaet": "JAEHRLICH",
      "notwendigkeitZweiteMessung": "VORHANDEN",
      "werteuebermittlungVerwendungszweck": "VORHANDEN",
      "artEMobilitaet": "LP",
      "konfigurationsprodukt": "voluptate laboris non",
      "keinKonfigurationsprodukt": true,
      "leistungskurvendefinition": "pariatur nostrud eiusmod anim",
      "verwendungszwecke": [
        {
          "marktrolle": "EIV",
          "zweck": [
            "BLINDARBEITSABRECHNUNG"
          ]
        }
      ]
    }
  ],
  "datenqualitaet": "GUELTIGE_DATEN",
  "zeitraumId": 5
}